setup.py
http_server_livereload/__init__.py
http_server_livereload.egg-info/PKG-INFO
http_server_livereload.egg-info/SOURCES.txt
http_server_livereload.egg-info/dependency_links.txt
http_server_livereload.egg-info/top_level.txt