Metadata-Version: 1.1
Name: http-server-livereload
Version: 1.1.0
Summary: A monkey patch of http.server to call livereload when server_forever is called. This is compatible with flask reload and tiny-lr (grunt watch).
Home-page: UNKNOWN
Author: Mounier Florian
Author-email: mounier.florian@gmail.com
License: MIT
Keywords: flask,livereload,grunt,watch,tiny-lr
Platform: Any
Classifier: Development Status :: 4 - Beta
Classifier: Intended Audience :: Developers
Classifier: Environment :: Console
Classifier: Operating System :: OS Independent
Classifier: Programming Language :: Python :: 2
Classifier: Programming Language :: Python :: 3
